plenpy/__init__.py
plenpy/_version.py
plenpy/lightfields.py
plenpy/logg.py
plenpy/spectral.py
plenpy/testing.py
plenpy/cameras/__init__.py
plenpy/cameras/abstract_camera.py
plenpy/cameras/abstract_lightfield_camera.py
plenpy/cameras/generic_lightfield_camera.py
plenpy/cameras/lytro_illum.py
plenpy/cameras/ms_lytro.py
plenpy/cameras/raytracer_lightfield_camera.py
plenpy/cameras/rgb_camera.py
plenpy/cameras/utils/__init__.py
plenpy/cameras/utils/sensor_image.py
plenpy/data/CMF_CIE1931_2deg_1nm.npy
plenpy/data/CMF_CIE1931_2deg_5nm.npy
plenpy/data/CMF_CIE1931_JUDD_2deg_5nm.npy
plenpy/data/CMF_CIE1931_JUDD_VOSS_2deg_5nm.npy
plenpy/data/CMF_CIE2006_2deg_0_1nm.npy
plenpy/data/CMF_CIE2006_2deg_1nm.npy
plenpy/data/CMF_CIE2006_2deg_5nm.npy
plenpy/data/ILLUMINANT_CIE_A.npy
plenpy/data/ILLUMINANT_CIE_D65.npy
plenpy/utilities/__init__.py
plenpy/utilities/colors.py
plenpy/utilities/core.py
plenpy/utilities/demosaic.py
plenpy/utilities/denoise.py
plenpy/utilities/grids.py
plenpy/utilities/images.py
plenpy/utilities/kernels.py
plenpy/utilities/misc.py
plenpy/utilities/plots.py
test/__init__.py
test/test_cameras_abstract_camera.py
test/test_cameras_abstract_lightfield_camera.py
test/test_cameras_lytro_illum.py
test/test_cameras_raytracer_lightfield_camera.py
test/test_cameras_rgb_camera.py
test/test_cameras_sensor_image.py
test/test_lightfields.py
test/test_spectral.py
test/test_utilities_colors.py
test/test_utilities_core.py
test/test_utilities_denoise.py
test/test_utilities_grids.py
test/test_utilities_images.py
test/test_utilities_kernels.py
test/test_utilities_misc.py
test/test_utilities_plots.py
plenpy-0.9.2.dist-info/AUTHORS
plenpy-0.9.2.dist-info/LICENSE
plenpy-0.9.2.dist-info/METADATA
plenpy-0.9.2.dist-info/WHEEL
plenpy-0.9.2.dist-info/top_level.txt
plenpy-0.9.2.dist-info/zip-safe
plenpy-0.9.2.dist-info/RECORD
