Metadata-Version: 2.1
Name: plenpy
Version: 0.9.2
Summary: A plenoptic processing library for Python.
Home-page: https://iiit-public.gitlab.io/plenpy/intro.html
Author: Maximilian Schambach
Author-email: schambach@kit.edu
License: GNU General Public License v3 (GPLv3)
Project-URL: Documentation, https://iiit-public.gitlab.io/plenpy/
Project-URL: Source, https://gitlab.com/iiit-public/plenpy
Project-URL: Research Group, https://www.iiit.kit.edu/english/3127.php
Platform: UNKNOWN
Classifier: Programming Language :: Python :: 3.6
Classifier: Programming Language :: Python :: 3.7
Classifier: Programming Language :: Python :: 3.8
Classifier: Programming Language :: Python :: 3.9
Classifier: License :: OSI Approved :: GNU General Public License v3 (GPLv3)
Classifier: Operating System :: OS Independent
Classifier: Development Status :: 4 - Beta
Requires-Python: >=3.6
License-File: LICENSE
License-File: AUTHORS
Requires-Dist: tqdm
Requires-Dist: h5py (>=2.0)
Requires-Dist: numPy (>=1.18)
Requires-Dist: scipy (>=1.1)
Requires-Dist: scikit-image (>=0.14)
Requires-Dist: matplotlib
Requires-Dist: imageio (>=2.11.1)
Requires-Dist: colour-science (>=0.3.15)
Requires-Dist: colour-demosaicing
Requires-Dist: joblib
Requires-Dist: jsmin
Provides-Extra: torch
Requires-Dist: torch ; extra == 'torch'
Requires-Dist: torchvision ; extra == 'torch'
